cppdep/__init__.py
cppdep/__main__.py
cppdep/config_schema.yml
cppdep/cppdep.py
cppdep/graph.py
cppdep-0.2.4.dist-info/DESCRIPTION.rst
cppdep-0.2.4.dist-info/METADATA
cppdep-0.2.4.dist-info/RECORD
cppdep-0.2.4.dist-info/WHEEL
cppdep-0.2.4.dist-info/entry_points.txt
cppdep-0.2.4.dist-info/metadata.json
cppdep-0.2.4.dist-info/top_level.txt
