Metadata-Version: 2.0
Name: cppdep
Version: 0.2.4
Summary: Dependency analyzer for C/C++ projects
Home-page: http://github.com/rakhimov/cppdep
Author: Olzhas Rakhimov
Author-email: ol.rakhimov@gmail.com
License: GPLv3+
Download-URL: https://github.com/rakhimov/cppdep
Keywords: c++,c,static analysis,dependency analysis
Platform: UNKNOWN
Classifier: Development Status :: 4 - Beta
Classifier: Intended Audience :: Developers
Classifier: Topic :: Software Development :: Quality Assurance
Classifier: License :: OSI Approved :: GNU General Public License v3 or later (GPLv3+)
Classifier: Programming Language :: C
Classifier: Programming Language :: C++
Classifier: Operating System :: POSIX
Classifier: Operating System :: Microsoft :: Windows
Classifier: Operating System :: MacOS :: MacOS X
Classifier: Environment :: Console
Classifier: Programming Language :: Python :: 2.7
Classifier: Programming Language :: Python :: 3.4
Classifier: Programming Language :: Python :: 3.5
Requires-Dist: networkx
Requires-Dist: pydot
Requires-Dist: pydotplus
Requires-Dist: PyYAML
Requires-Dist: PyKwalify (>=1.6.0)
